raspberry_sensors/__init__.py
raspberry_sensors/sensors.py
raspberry_sensors-2.1.2.dist-info/LICENSE
raspberry_sensors-2.1.2.dist-info/METADATA
raspberry_sensors-2.1.2.dist-info/WHEEL
raspberry_sensors-2.1.2.dist-info/top_level.txt
raspberry_sensors-2.1.2.dist-info/RECORD
