Metadata-Version: 2.1
Name: raspberry_sensors
Version: 2.1.2
Summary: This package for getting values from sensors mh_z19, DHT, ads1015
Author-email: Develper <testerlzt@mail.ru>
Keywords: raspberry_sensors,Adafruit-DHT,adafruit-circuitpython-ads1x15,mh-z19,raspberry,raspberry pi,sensors,hardware,IoT,Python
Classifier: Programming Language :: Python :: 3
Classifier: License :: OSI Approved :: MIT License
Classifier: Operating System :: OS Independent
Requires-Python: >=3.8
License-File: LICENSE
Requires-Dist: Adafruit-DHT
Requires-Dist: adafruit-circuitpython-ads1x15
Requires-Dist: mh-z19
